fhernandez-test/__init__.py
fhernandez-test/hello.py
fhernandeztest/__init__.py
fhernandeztest/hello.py
sayhellopackagefhernandez/__init__.py
sayhellopackagefhernandez/hello.py
sayhellopackagefhernandez-0.0.2.dist-info/LICENSE
sayhellopackagefhernandez-0.0.2.dist-info/METADATA
sayhellopackagefhernandez-0.0.2.dist-info/WHEEL
sayhellopackagefhernandez-0.0.2.dist-info/top_level.txt
sayhellopackagefhernandez-0.0.2.dist-info/RECORD
