Metadata-Version: 2.1
Name: sayhellopackagefhernandez
Version: 0.0.2
Summary: Say hello package
Home-page: UNKNOWN
Author: Felipe Hernandez
Author-email: <ingeingero@gmail.com>
License: UNKNOWN
Keywords: python
Platform: UNKNOWN
Classifier: Development Status :: 1 - Planning
Classifier: Intended Audience :: Developers
Classifier: Programming Language :: Python :: 3
Classifier: Operating System :: Unix
Classifier: Operating System :: MacOS :: MacOS X
Classifier: Operating System :: Microsoft :: Windows
